mcpc/__init__.py
mcpc/handler.py
mcpc/helper.py
mcpc/models.py
mcpc-0.2.6.dist-info/METADATA
mcpc-0.2.6.dist-info/WHEEL
mcpc-0.2.6.dist-info/licenses/LICENSE.md
mcpc-0.2.6.dist-info/RECORD
