Metadata-Version: 2.4
Name: mcpc
Version: 0.2.6
Summary: MCP Callback Protocol extension for enabling asynchronous tool callbacks and streaming updates from MCP clients
Project-URL: Homepage, https://github.com/OlaHulleberg/mcpc
Project-URL: Bug Tracker, https://github.com/OlaHulleberg/mcpc/issues
Project-URL: Documentation, https://github.com/OlaHulleberg/mcpc#readme
Author-email: Ola Hulleberg <ola@hulleberg.net>
License: MIT
License-File: LICENSE.md
Keywords: async,callbacks,mcp,protocol,streaming
Classifier: Development Status :: 4 - Beta
Classifier: Intended Audience :: Developers
Classifier: License :: OSI Approved :: MIT License
Classifier: Programming Language :: Python :: 3
Classifier: Programming Language :: Python :: 3.12
Classifier: Topic :: Software Development :: Libraries :: Python Modules
Requires-Python: >=3.12
Requires-Dist: mcp[cli]>=1.6.0
Requires-Dist: pydantic>=2.0.0
